easyvpn/__init__.py
easyvpn/pyarmor_runtime_000000/__init__.py
easyvpn-0.0.2.dist-info/LICENSE.txt
easyvpn-0.0.2.dist-info/METADATA
easyvpn-0.0.2.dist-info/WHEEL
easyvpn-0.0.2.dist-info/top_level.txt
easyvpn-0.0.2.dist-info/RECORD
