Metadata-Version: 2.1
Name: easyvpn
Version: 0.0.2
Summary: VPN package
Author: Ketuke
Author-email: clientCrank@gmail.com
License-File: LICENSE.txt
Requires-Dist: telebot
